locarc/__init__.py
locarc/callbacks.py
locarc/constants.py
locarc/errors.py
locarc/events.py
locarc/logger.py
locarc/main.py
locarc/models.py
locarc/py.typed
locarc/types.py
locarc/utils.py
locarc/providers/__init__.py
locarc/providers/inmemory.py
locarc/providers/pubsub.py
locarc-0.2.2.dist-info/METADATA
locarc-0.2.2.dist-info/WHEEL
locarc-0.2.2.dist-info/entry_points.txt
locarc-0.2.2.dist-info/RECORD
