Metadata-Version: 2.4
Name: locarc
Version: 0.2.2
Summary: A simple Python tools that aims to emulate EventArc behavior locally
Requires-Python: >=3.13
Requires-Dist: httpx>=0.28.1
Requires-Dist: pydantic-settings>=2.10.1
Requires-Dist: pydantic>=2.11.7
Requires-Dist: pyyaml>=6.0.2
Requires-Dist: typer>=0.16.1
Provides-Extra: pubsub
Requires-Dist: google-cloud-pubsub>=2.31.1; extra == 'pubsub'
